{
    "set": [
      { "id": 1, "img": "https://i.ibb.co/V260X1R/1.png" , "name": "Саломон сет", "weight": "1050", "pieces": "30", "price":"1500", "want": "false"},
      { "id": 2, "img": "https://i.ibb.co/JmSwM31/2.png" , "name": "Сет '5 Филадельфий'", "weight": "1120", "pieces": "40", "price":"1499", "want": "false"},
      { "id": 3, "img": "https://i.ibb.co/BtvnFNc/3.png" , "name": "Филадельфия и лосось сет", "weight": "1260", "pieces": "36", "price":"1499", "want": "false"},
      { "id": 4, "img": "https://i.ibb.co/TBjZmjw/4.png" , "name": "Сет '6 Филадельфий'", "weight": "1320", "pieces": "46", "price":"1559", "want": "false"},
      { "id": 5, "img": "https://i.ibb.co/DbJKGny/5.png" , "name": "Топовый сет", "weight": "1020", "pieces": "40", "price":"1519", "want": "false"},
      { "id": 6, "img": "https://i.ibb.co/8DWK8xW/6.png" , "name": "Камикадзе сет", "weight": "1200", "pieces": "52", "price":"1469", "want": "false"},
      { "id": 7, "img": "https://i.ibb.co/BnZyGYh/7.png" , "name": "Сет '4 Филадельфии'", "weight": "1100", "pieces": "32", "price":"1559", "want": "false"},
      { "id": 8, "img": "https://i.ibb.co/nbSKHDt/8.png" , "name": "Филадельфия LOVE сет", "weight": "1000", "pieces": "40", "price":"1479", "want": "false"},
      { "id": 9, "img": "https://i.ibb.co/V9rvnNF/9.png" , "name": "Якудза сет", "weight": "1270", "pieces": "50", "price":"1499", "want": "false"}
    ],
    "feedback": [
      { "id": 1, "name": "Розалия", "time": "02.24.21", "text": "Ваша доставка и ваши блюда лучшие в Харькове!) всегда очень вкусно, вовремя, всегда вежливые курьеры и девушки на телефоне"},
      { "id": 2, "name": "Елена", "time": "02.23.21", "text": "Ооочень вкусно!!!!!"},
      { "id": 3, "name": "Сергей Гаврилюк", "time": "02.23.21", "text": "Заказываем у Вас больше 2 -ух лет, были разные ситуации, но сервис стал лучше, суши вкуснее. За доставку сегодня на время, огромное спасибо, точь-в-точь в минута в минуту. Успехов Вам и приятных бонусов нам )"}
    ],
    "profile": { "name": "typicode" }
  }